iflags/flags.py
iflags-1.0.3.dist-info/LICENSE
iflags-1.0.3.dist-info/WHEEL
iflags-1.0.3.dist-info/METADATA
iflags-1.0.3.dist-info/RECORD
