Metadata-Version: 2.1
Name: iflags
Version: 1.0.3
Summary: A Generic flags parser based on argparse
License: MIT
Author: maybaby
Author-email: ybyang7@iflytek.com
Requires-Python: >3.6
Classifier: License :: OSI Approved :: MIT License
Classifier: Programming Language :: Python :: 3
Classifier: Programming Language :: Python :: 3.10
Classifier: Programming Language :: Python :: 3.7
Classifier: Programming Language :: Python :: 3.8
Classifier: Programming Language :: Python :: 3.9
